pygacity/__init__.py
pygacity/cli.py
pygacity/generate/__init__.py
pygacity/generate/answerset.py
pygacity/generate/block.py
pygacity/generate/build.py
pygacity/generate/config.py
pygacity/generate/document.py
pygacity/generate/latexcompiler.py
pygacity/generate/pick.py
pygacity/resources/__init__.py
pygacity/resources/autoprob-package/tex/latex/autoprob.cls
pygacity/resources/corresponding-states-data/enthalpy-departures.csv
pygacity/resources/corresponding-states-data/enthalpy-departures.raw
pygacity/resources/corresponding-states-data/entropy-departures.csv
pygacity/resources/corresponding-states-data/entropy-departures.raw
pygacity/resources/pythontex/chemeq.pycode
pygacity/resources/pythontex/matplotlib.pycode
pygacity/resources/pythontex/sandlerprops.pycode
pygacity/resources/pythontex/sandlersteam.pycode
pygacity/resources/pythontex/setup.pycode
pygacity/resources/pythontex/showsteamtables.pycode
pygacity/resources/pythontex/teardown.pycode
pygacity/resources/templates/footer.tex
pygacity/resources/templates/header.tex
pygacity/resources/templates/short.tex
pygacity/topics/__init__.py
pygacity/topics/chem/__init__.py
pygacity/topics/chem/chemeqsystem.py
pygacity/topics/chem/compound.py
pygacity/topics/chem/properties.py
pygacity/topics/chem/reaction.py
pygacity/topics/distillation/__init__.py
pygacity/topics/distillation/binaryduties.py
pygacity/topics/distillation/binaryflashdepriester.py
pygacity/topics/distillation/fug.py
pygacity/topics/distillation/mccabethiele.py
pygacity/topics/steam/__init__.py
pygacity/topics/steam/steamtank.py
pygacity/topics/thermo/__init__.py
pygacity/topics/thermo/corrsts.py
pygacity/topics/thermo/cubics.py
pygacity/topics/vle/__init__.py
pygacity/topics/vle/txyplot.py
pygacity/topics/vle/vle.py
pygacity/util/__init__.py
pygacity/util/collectors.py
pygacity/util/command.py
pygacity/util/corrsts_wpd2csv.py
pygacity/util/pdfutils.py
pygacity/util/stringthings.py
pygacity/util/texutils.py
pygacity-0.6.0.dist-info/METADATA
pygacity-0.6.0.dist-info/WHEEL
pygacity-0.6.0.dist-info/entry_points.txt
pygacity-0.6.0.dist-info/licenses/LICENSE
pygacity-0.6.0.dist-info/RECORD
