Metadata-Version: 2.4
Name: pygacity
Version: 0.6.0
Summary: A framework for exam and assignment generation using LaTeX and pythontex
Author-email: Cameron F Abrams <cfa22@drexel.edu>
License-File: LICENSE
Classifier: License :: OSI Approved :: MIT License
Classifier: Programming Language :: Python :: 3
Requires-Python: >=3.7
Requires-Dist: iapws
Requires-Dist: jinja2
Requires-Dist: numpy
Requires-Dist: pandas
Requires-Dist: progressbar
Requires-Dist: pypdf2
Requires-Dist: roman
Requires-Dist: sandlerprops
Requires-Dist: sandlersteam
Requires-Dist: scipy
